payload_dumper/__init__.py
payload_dumper/dumper.py
payload_dumper/update_metadata_pb2.py
payload_dumper-0.2.2.dist-info/entry_points.txt
payload_dumper-0.2.2.dist-info/WHEEL
payload_dumper-0.2.2.dist-info/METADATA
payload_dumper-0.2.2.dist-info/RECORD
