Metadata-Version: 2.1
Name: payload-dumper
Version: 0.2.2
Summary: Dump partitions from Android's payload.bin
Home-page: https://github.com/nnsee/payload-dumper
Author: Rasmus Moorats
Author-email: xx@nns.ee
Requires-Python: >=3.7
Classifier: Programming Language :: Python :: 3
Classifier: Programming Language :: Python :: 3.10
Classifier: Programming Language :: Python :: 3.7
Classifier: Programming Language :: Python :: 3.8
Classifier: Programming Language :: Python :: 3.9
Requires-Dist: bsdiff4 (>=1.2.1,<2.0.0)
Requires-Dist: enlighten (>=1.10.2,<2.0.0)
Requires-Dist: protobuf (>=3.19.1,<4.0.0)
Project-URL: Repository, https://github.com/nnsee/payload-dumper
